{
  "filename": "Screenshot_0096.jpg",
  "items": [
    {
      "text": "17:20 {,0 M",
      "box": [
        [
          36.0,
          24.0
        ],
        [
          296.0,
          24.0
        ],
        [
          296.0,
          74.0
        ],
        [
          36.0,
          74.0
        ]
      ],
      "conf": 0.3525
    },
    {
      "text": "954",
      "box": [
        [
          966.0,
          32.0
        ],
        [
          1034.0,
          32.0
        ],
        [
          1034.0,
          64.0
        ],
        [
          966.0,
          64.0
        ]
      ],
      "conf": 0.4394
    },
    {
      "text": "Explorar",
      "box": [
        [
          183.0,
          121.0
        ],
        [
          413.0,
          121.0
        ],
        [
          413.0,
          183.0
        ],
        [
          183.0,
          183.0
        ]
      ],
      "conf": 0.7165
    },
    {
      "text": "02h 32m 58s",
      "box": [
        [
          85.0,
          187.0
        ],
        [
          312.0,
          187.0
        ],
        [
          312.0,
          229.0
        ],
        [
          85.0,
          229.0
        ]
      ],
      "conf": 0.9395
    },
    {
      "text": "36,8 mil",
      "box": [
        [
          939.0,
          1367.0
        ],
        [
          1065.0,
          1367.0
        ],
        [
          1065.0,
          1403.0
        ],
        [
          939.0,
          1403.0
        ]
      ],
      "conf": 0.9654
    },
    {
      "text": "385",
      "box": [
        [
          970.0,
          1546.0
        ],
        [
          1034.0,
          1546.0
        ],
        [
          1034.0,
          1578.0
        ],
        [
          970.0,
          1578.0
        ]
      ],
      "conf": 1.0
    },
    {
      "text": "thev literally thought that",
      "box": [
        [
          301.0,
          1580.0
        ],
        [
          778.0,
          1580.0
        ],
        [
          778.0,
          1637.0
        ],
        [
          301.0,
          1637.0
        ]
      ],
      "conf": 0.7667
    },
    {
      "text": "all people think about",
      "box": [
        [
          338.0,
          1632.0
        ],
        [
          744.0,
          1632.0
        ],
        [
          744.0,
          1686.0
        ],
        [
          338.0,
          1686.0
        ]
      ],
      "conf": 0.9879
    },
    {
      "text": "Indians is that we're smart",
      "box": [
        [
          295.0,
          1683.0
        ],
        [
          785.0,
          1683.0
        ],
        [
          785.0,
          1728.0
        ],
        [
          295.0,
          1728.0
        ]
      ],
      "conf": 0.9723
    },
    {
      "text": "11",
      "box": [
        [
          986.0,
          1724.0
        ],
        [
          1018.0,
          1724.0
        ],
        [
          1018.0,
          1754.0
        ],
        [
          986.0,
          1754.0
        ]
      ],
      "conf": 0.9956
    },
    {
      "text": "CLUBBING",
      "box": [
        [
          65.0,
          1883.0
        ],
        [
          113.0,
          1883.0
        ],
        [
          113.0,
          1903.0
        ],
        [
          65.0,
          1903.0
        ]
      ],
      "conf": 0.6672
    },
    {
      "text": "malluclubbing",
      "box": [
        [
          153.0,
          1849.0
        ],
        [
          414.0,
          1849.0
        ],
        [
          414.0,
          1904.0
        ],
        [
          153.0,
          1904.0
        ]
      ],
      "conf": 1.0
    },
    {
      "text": "Seguir",
      "box": [
        [
          466.0,
          1856.0
        ],
        [
          592.0,
          1856.0
        ],
        [
          592.0,
          1906.0
        ],
        [
          466.0,
          1906.0
        ]
      ],
      "conf": 1.0
    },
    {
      "text": "0",
      "box": [
        [
          716.0,
          2090.0
        ],
        [
          798.0,
          2090.0
        ],
        [
          798.0,
          2162.0
        ],
        [
          716.0,
          2162.0
        ]
      ],
      "conf": 0.9776
    }
  ]
}