{
  "filename": "Screenshot_0082.jpg",
  "items": [
    {
      "text": "8:30",
      "box": [
        [
          154.0,
          62.0
        ],
        [
          278.0,
          62.0
        ],
        [
          278.0,
          116.0
        ],
        [
          154.0,
          116.0
        ]
      ],
      "conf": 0.5364
    },
    {
      "text": "STEM",
      "box": [
        [
          187.0,
          221.0
        ],
        [
          293.0,
          221.0
        ],
        [
          293.0,
          265.0
        ],
        [
          187.0,
          265.0
        ]
      ],
      "conf": 0.6355
    },
    {
      "text": "Explore",
      "box": [
        [
          328.0,
          220.0
        ],
        [
          470.0,
          220.0
        ],
        [
          470.0,
          274.0
        ],
        [
          328.0,
          274.0
        ]
      ],
      "conf": 1.0
    },
    {
      "text": "Following",
      "box": [
        [
          502.0,
          210.0
        ],
        [
          691.0,
          210.0
        ],
        [
          691.0,
          282.0
        ],
        [
          502.0,
          282.0
        ]
      ],
      "conf": 1.0
    },
    {
      "text": "Shop",
      "box": [
        [
          715.0,
          214.0
        ],
        [
          825.0,
          214.0
        ],
        [
          825.0,
          279.0
        ],
        [
          715.0,
          279.0
        ]
      ],
      "conf": 0.9999
    },
    {
      "text": "For You",
      "box": [
        [
          848.0,
          219.0
        ],
        [
          997.0,
          219.0
        ],
        [
          997.0,
          268.0
        ],
        [
          848.0,
          268.0
        ]
      ],
      "conf": 0.9711
    },
    {
      "text": "Q",
      "box": [
        [
          1066.0,
          212.0
        ],
        [
          1122.0,
          212.0
        ],
        [
          1122.0,
          278.0
        ],
        [
          1066.0,
          278.0
        ]
      ],
      "conf": 0.3972
    },
    {
      "text": "Ithink he",
      "box": [
        [
          156.0,
          740.0
        ],
        [
          504.0,
          740.0
        ],
        [
          504.0,
          820.0
        ],
        [
          156.0,
          820.0
        ]
      ],
      "conf": 0.8971
    },
    {
      "text": "finally got the",
      "box": [
        [
          495.0,
          727.0
        ],
        [
          1027.0,
          727.0
        ],
        [
          1027.0,
          842.0
        ],
        [
          495.0,
          842.0
        ]
      ],
      "conf": 0.7475
    },
    {
      "text": "hint",
      "box": [
        [
          504.0,
          838.0
        ],
        [
          662.0,
          838.0
        ],
        [
          662.0,
          918.0
        ],
        [
          504.0,
          918.0
        ]
      ],
      "conf": 0.9999
    },
    {
      "text": "256.5K",
      "box": [
        [
          1021.0,
          1444.0
        ],
        [
          1155.0,
          1444.0
        ],
        [
          1155.0,
          1484.0
        ],
        [
          1021.0,
          1484.0
        ]
      ],
      "conf": 0.994
    },
    {
      "text": "284",
      "box": [
        [
          1047.0,
          1641.0
        ],
        [
          1127.0,
          1641.0
        ],
        [
          1127.0,
          1683.0
        ],
        [
          1047.0,
          1683.0
        ]
      ],
      "conf": 0.6812
    },
    {
      "text": "6,921",
      "box": [
        [
          1034.0,
          1836.0
        ],
        [
          1138.0,
          1836.0
        ],
        [
          1138.0,
          1885.0
        ],
        [
          1034.0,
          1885.0
        ]
      ],
      "conf": 1.0
    },
    {
      "text": "2,273",
      "box": [
        [
          1033.0,
          2039.0
        ],
        [
          1141.0,
          2039.0
        ],
        [
          1141.0,
          2083.0
        ],
        [
          1033.0,
          2083.0
        ]
      ],
      "conf": 0.8941
    },
    {
      "text": "msjacksonsecret",
      "box": [
        [
          33.0,
          2123.0
        ],
        [
          433.0,
          2123.0
        ],
        [
          433.0,
          2187.0
        ],
        [
          33.0,
          2187.0
        ]
      ],
      "conf": 0.9999
    },
    {
      "text": "Shhh don't tell my best friend",
      "box": [
        [
          32.0,
          2220.0
        ],
        [
          652.0,
          2220.0
        ],
        [
          652.0,
          2276.0
        ],
        [
          32.0,
          2276.0
        ]
      ],
      "conf": 0.9208
    },
    {
      "text": "36",
      "box": [
        [
          839.0,
          2319.0
        ],
        [
          891.0,
          2319.0
        ],
        [
          891.0,
          2357.0
        ],
        [
          839.0,
          2357.0
        ]
      ],
      "conf": 0.9665
    },
    {
      "text": "Home",
      "box": [
        [
          73.0,
          2405.0
        ],
        [
          165.0,
          2405.0
        ],
        [
          165.0,
          2437.0
        ],
        [
          73.0,
          2437.0
        ]
      ],
      "conf": 1.0
    },
    {
      "text": "Friends",
      "box": [
        [
          296.0,
          2406.0
        ],
        [
          412.0,
          2406.0
        ],
        [
          412.0,
          2438.0
        ],
        [
          296.0,
          2438.0
        ]
      ],
      "conf": 1.0
    },
    {
      "text": "Inbox",
      "box": [
        [
          780.0,
          2406.0
        ],
        [
          870.0,
          2406.0
        ],
        [
          870.0,
          2438.0
        ],
        [
          780.0,
          2438.0
        ]
      ],
      "conf": 0.9998
    },
    {
      "text": "Profile",
      "box": [
        [
          1010.0,
          2406.0
        ],
        [
          1114.0,
          2406.0
        ],
        [
          1114.0,
          2438.0
        ],
        [
          1010.0,
          2438.0
        ]
      ],
      "conf": 0.6668
    }
  ]
}