{
  "filename": "Screenshot_0056.jpg",
  "items": [
    {
      "text": "8.48",
      "box": [
        [
          35.0,
          25.0
        ],
        [
          131.0,
          25.0
        ],
        [
          131.0,
          67.0
        ],
        [
          35.0,
          67.0
        ]
      ],
      "conf": 0.8233
    },
    {
      "text": "0 <5",
      "box": [
        [
          835.0,
          29.0
        ],
        [
          925.0,
          29.0
        ],
        [
          925.0,
          67.0
        ],
        [
          835.0,
          67.0
        ]
      ],
      "conf": 0.3566
    },
    {
      "text": "Con",
      "box": [
        [
          184.0,
          122.0
        ],
        [
          294.0,
          122.0
        ],
        [
          294.0,
          174.0
        ],
        [
          184.0,
          174.0
        ]
      ],
      "conf": 0.9842
    },
    {
      "text": "amigos",
      "box": [
        [
          290.0,
          112.0
        ],
        [
          497.0,
          112.0
        ],
        [
          497.0,
          196.0
        ],
        [
          290.0,
          196.0
        ]
      ],
      "conf": 1.0
    },
    {
      "text": "01h 35m 51s",
      "box": [
        [
          83.0,
          187.0
        ],
        [
          311.0,
          187.0
        ],
        [
          311.0,
          229.0
        ],
        [
          83.0,
          229.0
        ]
      ],
      "conf": 0.6308
    },
    {
      "text": "Passengerprincessor",
      "box": [
        [
          311.0,
          409.0
        ],
        [
          770.0,
          409.0
        ],
        [
          770.0,
          485.0
        ],
        [
          311.0,
          485.0
        ]
      ],
      "conf": 0.9999
    },
    {
      "text": "passengervictim",
      "box": [
        [
          326.0,
          472.0
        ],
        [
          682.0,
          472.0
        ],
        [
          682.0,
          544.0
        ],
        [
          326.0,
          544.0
        ]
      ],
      "conf": 0.6569
    },
    {
      "text": "284",
      "box": [
        [
          944.0,
          1366.0
        ],
        [
          1010.0,
          1366.0
        ],
        [
          1010.0,
          1398.0
        ],
        [
          944.0,
          1398.0
        ]
      ],
      "conf": 1.0
    },
    {
      "text": "1.058",
      "box": [
        [
          960.0,
          1544.0
        ],
        [
          1046.0,
          1544.0
        ],
        [
          1046.0,
          1576.0
        ],
        [
          960.0,
          1576.0
        ]
      ],
      "conf": 1.0
    },
    {
      "text": "133 mil",
      "box": [
        [
          948.0,
          1722.0
        ],
        [
          1058.0,
          1722.0
        ],
        [
          1058.0,
          1754.0
        ],
        [
          948.0,
          1754.0
        ]
      ],
      "conf": 0.82
    },
    {
      "text": "strawhatdan y beingbeefr",
      "box": [
        [
          149.0,
          1782.0
        ],
        [
          604.0,
          1782.0
        ],
        [
          604.0,
          1834.0
        ],
        [
          149.0,
          1834.0
        ]
      ],
      "conf": 0.9542
    },
    {
      "text": "Seguir",
      "box": [
        [
          656.0,
          1788.0
        ],
        [
          782.0,
          1788.0
        ],
        [
          782.0,
          1836.0
        ],
        [
          656.0,
          1836.0
        ]
      ],
      "conf": 0.7348
    },
    {
      "text": "Mind u im on my Deriod",
      "box": [
        [
          38.0,
          1892.0
        ],
        [
          448.0,
          1892.0
        ],
        [
          448.0,
          1943.0
        ],
        [
          38.0,
          1943.0
        ]
      ],
      "conf": 0.942
    },
    {
      "text": "Ver traduccion",
      "box": [
        [
          39.0,
          1953.0
        ],
        [
          305.0,
          1953.0
        ],
        [
          305.0,
          1993.0
        ],
        [
          39.0,
          1993.0
        ]
      ],
      "conf": 0.9794
    },
    {
      "text": "Enviar mensaje a fadrian:_.",
      "box": [
        [
          101.0,
          2095.0
        ],
        [
          553.0,
          2095.0
        ],
        [
          553.0,
          2139.0
        ],
        [
          101.0,
          2139.0
        ]
      ],
      "conf": 0.7
    },
    {
      "text": "mil",
      "box": [
        [
          1006.4615384615385,
          1366.3076923076924
        ],
        [
          1063.2549338848269,
          1362.6750472251235
        ],
        [
          1064.5384615384614,
          1397.6923076923076
        ],
        [
          1007.745066115173,
          1402.3249527748765
        ]
      ],
      "conf": 0.9999
    }
  ]
}